visionsim/__init__.py
visionsim/types.py
visionsim/cli/__init__.py
visionsim/cli/blender.py
visionsim/cli/dataset.py
visionsim/cli/emulate.py
visionsim/cli/ffmpeg.py
visionsim/cli/interpolate.py
visionsim/cli/transforms.py
visionsim/dataset/__init__.py
visionsim/dataset/dataset.py
visionsim/dataset/schema.py
visionsim/emulate/__init__.py
visionsim/emulate/imu.py
visionsim/emulate/rgb.py
visionsim/emulate/spc.py
visionsim/emulate/dvs/__init__.py
visionsim/emulate/dvs/v2e/emulator.py
visionsim/emulate/dvs/v2e/emulator_utils.py
visionsim/interpolate/__init__.py
visionsim/interpolate/pose.py
visionsim/interpolate/rife/IFNet_HDv3.py
visionsim/interpolate/rife/RIFE_HDv3.py
visionsim/interpolate/rife/__init__.py
visionsim/interpolate/rife/inference_img.py
visionsim/interpolate/rife/warplayer.py
visionsim/simulate/__init__.py
visionsim/simulate/blender.py
visionsim/simulate/blender.pyi
visionsim/simulate/config.py
visionsim/simulate/install.py
visionsim/simulate/job.py
visionsim/simulate/nodes/__init__.py
visionsim/simulate/nodes/common.py
visionsim/simulate/nodes/flow.py
visionsim/simulate/nodes/normals.py
visionsim/simulate/nodes/segmentation.py
visionsim/utils/__init__.py
visionsim/utils/color.py
visionsim/utils/progress.py
visionsim-0.1.0a2.dist-info/METADATA
visionsim-0.1.0a2.dist-info/WHEEL
visionsim-0.1.0a2.dist-info/entry_points.txt
visionsim-0.1.0a2.dist-info/licenses/LICENSE
visionsim-0.1.0a2.dist-info/RECORD
